meg/__init__.py
meg/converters.py
meg/engine.py
meg/libengine.py
meg/libmatrix.py
meg/library.py
meg-1.0.1.dist-info/LICENSE
meg-1.0.1.dist-info/METADATA
meg-1.0.1.dist-info/WHEEL
meg-1.0.1.dist-info/top_level.txt
meg-1.0.1.dist-info/RECORD
