Metadata-Version: 2.1
Name: meg
Version: 1.0.1
Summary: MATLAB engine connector
Home-page: https://github.com/lamyj/meg/
Author: Julien Lamy
Author-email: lamy@unistra.fr
License: MIT
Keywords: MATLAB,engine,bridge
Platform: UNKNOWN
Classifier: Development Status :: 4 - Beta
Classifier: Environment :: Console
Classifier: Intended Audience :: Education
Classifier: Intended Audience :: Science/Research
Classifier: License :: OSI Approved :: MIT License
Classifier: Programming Language :: Python :: 3
Classifier: Topic :: Scientific/Engineering
Requires-Python: >=3.5
License-File: LICENSE
Requires-Dist: numpy
